madarrays/__init__.py
madarrays/mad_array.py
madarrays/waveform.py
madarrays/tests/__init__.py
madarrays/tests/test_madarray.py
madarrays/tests/test_waveform.py
madarrays/tests/utils.py
madarrays-1.1.2.dist-info/DESCRIPTION.rst
madarrays-1.1.2.dist-info/METADATA
madarrays-1.1.2.dist-info/RECORD
madarrays-1.1.2.dist-info/WHEEL
madarrays-1.1.2.dist-info/metadata.json
madarrays-1.1.2.dist-info/top_level.txt
