Metadata-Version: 2.0
Name: madarrays
Version: 1.1.2
Summary: Python package for audio data structures with missing entries
Home-page: https://gitlab.lis-lab.fr/skmad-suite/madarrays
Author: Ronan Hamon, Valentin Emiya, and Florent Jaillet
Author-email: ronan.hamon@lis-lab.fr, valentin.emiya@lis-lab.fr, florent.jaillet@lis-lab.fr
License: GNU General Public License v3 (GPLv3)
Project-URL: Bug Reports, https://gitlab.lis-lab.fr/skmad-suite/madarrays/issues
Project-URL: Source, https://gitlab.lis-lab.fr/skmad-suite/madarrays
Keywords: audio,data structures,missing data
Platform: UNKNOWN
Classifier: Development Status :: 5 - Production/Stable
Classifier: Intended Audience :: Developers
Classifier: Intended Audience :: End Users/Desktop
Classifier: Intended Audience :: Science/Research
Classifier: Topic :: Multimedia :: Sound/Audio :: Analysis
Classifier: Topic :: Scientific/Engineering :: Artificial Intelligence
Classifier: Topic :: Scientific/Engineering :: Mathematics
Classifier: License :: OSI Approved :: GNU General Public License v3 (GPLv3)
Classifier: Natural Language :: English
Classifier: Operating System :: MacOS :: MacOS X 
Classifier: Operating System :: POSIX :: Linux
Classifier: Programming Language :: Python :: 3.5
Classifier: Programming Language :: Python :: 3.6
Requires-Python: >=3.5
Provides-Extra: dev
Provides-Extra: doc
Requires-Dist: matplotlib
Requires-Dist: numpy
Requires-Dist: scipy
Requires-Dist: simpleaudio
Requires-Dist: resampy
Provides-Extra: dev
Requires-Dist: coverage; extra == 'dev'
Requires-Dist: pytest; extra == 'dev'
Requires-Dist: pytest-cov; extra == 'dev'
Requires-Dist: pytest-randomly; extra == 'dev'
Requires-Dist: ipython; extra == 'dev'
Provides-Extra: doc
Requires-Dist: sphinx; extra == 'doc'
Requires-Dist: nbsphinx; extra == 'doc'
Requires-Dist: numpydoc; extra == 'doc'
